bt_recover/__init__.py
bt_recover/__main__.py
bt_recover/__version__.py
bt_recover/cli.py
bt_recover/config.py
bt_recover/exceptions.py
bt_recover/main.py
bt_recover/monitoring.py
bt_recover/progress.py
bt_recover-0.1.7.dist-info/METADATA
bt_recover-0.1.7.dist-info/WHEEL
bt_recover-0.1.7.dist-info/entry_points.txt
bt_recover-0.1.7.dist-info/licenses/LICENSE
bt_recover-0.1.7.dist-info/RECORD
