Metadata-Version: 2.4
Name: bt-recover
Version: 0.1.7
Summary: Download BrightTalk videos from m3u8 streams
Project-URL: Homepage, https://github.com/KevinOBytes/bt-recover
Project-URL: Documentation, https://github.com/KevinOBytes/bt-recover#readme
Project-URL: Issues, https://github.com/KevinOBytes/bt-recover/issues
Author-email: Kevin O'Connor <kevin@kevinbytes.com>
License-Expression: MIT
License-File: LICENSE
Keywords: brighttalk,downloader,m3u8,video
Classifier: Environment :: Console
Classifier: License :: OSI Approved :: MIT License
Classifier: Operating System :: OS Independent
Classifier: Programming Language :: Python
Classifier: Programming Language :: Python :: 3
Classifier: Programming Language :: Python :: 3.10
Classifier: Programming Language :: Python :: 3.11
Classifier: Programming Language :: Python :: 3.12
Classifier: Topic :: Multimedia :: Video
Classifier: Topic :: Utilities
Requires-Python: >=3.10
Requires-Dist: ffmpeg-python>=0.2.0
Requires-Dist: requests>=2.31.0
Requires-Dist: tqdm>=4.65.0
Provides-Extra: dev
Requires-Dist: black>=23.12.1; extra == 'dev'
Requires-Dist: flake8>=6.0.0; extra == 'dev'
Requires-Dist: mypy>=1.0.0; extra == 'dev'
Requires-Dist: pre-commit>=3.5.0; extra == 'dev'
Requires-Dist: pytest-cov>=4.1.0; extra == 'dev'
Requires-Dist: pytest>=7.0.0; extra == 'dev'
Requires-Dist: tox>=4.11.4; extra == 'dev'
Requires-Dist: types-requests>=2.31.0; extra == 'dev'
Provides-Extra: test
Requires-Dist: pytest-cov>=4.1.0; extra == 'test'
Requires-Dist: pytest-mock>=3.10.0; extra == 'test'
Requires-Dist: pytest>=7.0.0; extra == 'test'
